django_gateway_interface/__init__.py
django_gateway_interface/manage.py
django_gateway_interface/gateapp/__init__.py
django_gateway_interface/gateapp/admin.py
django_gateway_interface/gateapp/apps.py
django_gateway_interface/gateapp/form.py
django_gateway_interface/gateapp/models.py
django_gateway_interface/gateapp/tests.py
django_gateway_interface/gateapp/urls.py
django_gateway_interface/gateapp/views.py
django_gateway_interface/gateapp/migrations/__init__.py
django_gateway_interface/gatewayApplication/__init__.py
django_gateway_interface/gatewayApplication/asgi.py
django_gateway_interface/gatewayApplication/settings.py
django_gateway_interface/gatewayApplication/urls.py
django_gateway_interface/gatewayApplication/wsgi.py
django_gateway_interface-0.1.5.dist-info/LICENSE
django_gateway_interface-0.1.5.dist-info/METADATA
django_gateway_interface-0.1.5.dist-info/WHEEL
django_gateway_interface-0.1.5.dist-info/top_level.txt
django_gateway_interface-0.1.5.dist-info/RECORD
